emptyspacesearch-0.3.1.dist-info/licenses/LICENSE
ess/__init__.py
ess/ess.py
ess/legacy.py
ess/nn.py
ess/utils.py
emptyspacesearch-0.3.1.dist-info/METADATA
emptyspacesearch-0.3.1.dist-info/WHEEL
emptyspacesearch-0.3.1.dist-info/top_level.txt
emptyspacesearch-0.3.1.dist-info/RECORD
