Metadata-Version: 2.4
Name: EmptySpaceSearch
Version: 0.3.1
Summary: Empty Space Search
Home-page: https://github.com/mariolpantunes/ess
Author: Mário Antunes
Author-email: mario.antunes@ua.pt
Project-URL: Homepage, https://github.com/mariolpantunes/ess
Project-URL: Documentation, https://mariolpantunes.github.io/ess/
Project-URL: Repository, https://github.com/mariolpantunes/ess
Project-URL: Issues, https://github.com/mariolpantunes/ess/issues
Classifier: Programming Language :: Python :: 3
Classifier: License :: OSI Approved :: MIT License
Classifier: Operating System :: OS Independent
Requires-Python: >=3.10
License-File: LICENSE
Requires-Dist: numpy>=2.0.0
Requires-Dist: faiss-cpu>=1.8.0
Dynamic: license-file
